setup.py
parse_client/__init__.py
parse_client/config.py
parse_client/connection.py
parse_client/core.py
parse_client/datatypes.py
parse_client/installation.py
parse_client/query.py
parse_client/role.py
parse_client/test_relations.py
parse_client/tests.py
parse_client/user.py
parse_client.egg-info/PKG-INFO
parse_client.egg-info/SOURCES.txt
parse_client.egg-info/dependency_links.txt
parse_client.egg-info/requires.txt
parse_client.egg-info/top_level.txt
parse_client/cloudcode/cloud/main.js